pastperfect/__init__.py
pastperfect/events.py
pastperfect-0.3.1.dist-info/LICENSE
pastperfect-0.3.1.dist-info/METADATA
pastperfect-0.3.1.dist-info/WHEEL
pastperfect-0.3.1.dist-info/RECORD
